powerline_travis_ci/__init__.py
powerline_travis_ci/travis.py
powerline_travis_ci-0.1.post1.dist-info/LICENSE
powerline_travis_ci-0.1.post1.dist-info/METADATA
powerline_travis_ci-0.1.post1.dist-info/WHEEL
powerline_travis_ci-0.1.post1.dist-info/top_level.txt
powerline_travis_ci-0.1.post1.dist-info/RECORD
