Metadata-Version: 2.1
Name: powerline-travis-ci
Version: 0.1.post1
Summary: A Powerline segment for fetching and showing the latest travis-ci build state
Home-page: https://github.com/DeepSpace2/powerline-travis-ci
Author: DeepSpace2
Author-email: deepspace2@gmail.com
License: MIT
Keywords: powerline travis-ci travis ci build state status segment terminal cli
Platform: UNKNOWN
Classifier: Environment :: Console
Classifier: Intended Audience :: Developers
Classifier: License :: OSI Approved :: MIT License
Classifier: Topic :: Terminals
